LICENSE
README.md
setup.py
DownloadBar.egg-info/PKG-INFO
DownloadBar.egg-info/SOURCES.txt
DownloadBar.egg-info/dependency_links.txt
DownloadBar.egg-info/entry_points.txt
DownloadBar.egg-info/top_level.txt
src/__init__.py
src/main.py