Metadata-Version: 2.1
Name: DownloadBar
Version: 0.1.0
Summary: A simple package for displaying the download progress bar with percentage in Command Line
Home-page: UNKNOWN
Author: Dikshant Ghimire
Author-email: dikkughimire@gmal.com
License: UNKNOWN
Platform: UNKNOWN
Classifier: Programming Language :: Python :: 3
Classifier: License :: OSI Approved :: MIT License
Classifier: Operating System :: OS Independent
Requires-Python: >=3.6
License-File: LICENSE
